astroSynth/PVS.py
astroSynth/SDM.py
astroSynth/__init__.py
astroSynth/Objects/POS.py
astroSynth/Objects/__init__.py
astroSynth-0.6.1.6.dist-info/DESCRIPTION.rst
astroSynth-0.6.1.6.dist-info/METADATA
astroSynth-0.6.1.6.dist-info/RECORD
astroSynth-0.6.1.6.dist-info/WHEEL
astroSynth-0.6.1.6.dist-info/metadata.json
astroSynth-0.6.1.6.dist-info/top_level.txt
