Metadata-Version: 2.0
Name: astroSynth
Version: 0.6.1.6
Summary: Very Basic Astrophysics Synthetic Generation Suite
Home-page: https://github.com/tboudreaux/astroSynth.git
Author: Thomas Boudreaux
Author-email: thomas@boudreauxmail.com
License: MIT
Platform: UNKNOWN
Classifier: Development Status :: 4 - Beta
Classifier: Intended Audience :: Science/Research
Classifier: License :: OSI Approved :: MIT License
Classifier: Programming Language :: Python :: 3
Requires-Dist: astropy (>=1.3.2)
Requires-Dist: names (>=0.3.0)
Requires-Dist: numpy (>=1.12.0)
Requires-Dist: pandas (>=0.19.2)
Requires-Dist: scipy (>=0.19.0)
Requires-Dist: tqdm (>=4.11.2)
